PlasAnn/__init__.py
PlasAnn/annotate_plasmid.py
PlasAnn/draw_plasmid.py
PlasAnn/essential_annotation.py
PlasMap-1.1.dist-info/METADATA
PlasMap-1.1.dist-info/WHEEL
PlasMap-1.1.dist-info/entry_points.txt
PlasMap-1.1.dist-info/top_level.txt
PlasMap-1.1.dist-info/RECORD
